fds/__init__.py
fds/sdk/__init__.py
fds/sdk/BookBuilder/__init__.py
fds/sdk/BookBuilder/api_client.py
fds/sdk/BookBuilder/configuration.py
fds/sdk/BookBuilder/exceptions.py
fds/sdk/BookBuilder/model_utils.py
fds/sdk/BookBuilder/rest.py
fds/sdk/BookBuilder/api/__init__.py
fds/sdk/BookBuilder/api/books___creation_api.py
fds/sdk/BookBuilder/api/books___fetch_api.py
fds/sdk/BookBuilder/api/custom_documents___fetch_api.py
fds/sdk/BookBuilder/api/custom_documents___upload_api.py
fds/sdk/BookBuilder/api/templates___creation_api.py
fds/sdk/BookBuilder/api/templates___fetch_api.py
fds/sdk/BookBuilder/apis/__init__.py
fds/sdk/BookBuilder/model/__init__.py
fds/sdk/BookBuilder/model/available_reports_list.py
fds/sdk/BookBuilder/model/book_info.py
fds/sdk/BookBuilder/model/book_processing_response.py
fds/sdk/BookBuilder/model/book_processing_response_item.py
fds/sdk/BookBuilder/model/content_section.py
fds/sdk/BookBuilder/model/create_book_from_template_post_request.py
fds/sdk/BookBuilder/model/create_book_post_request.py
fds/sdk/BookBuilder/model/create_template_post_request.py
fds/sdk/BookBuilder/model/enable_book_download.py
fds/sdk/BookBuilder/model/enable_book_info.py
fds/sdk/BookBuilder/model/enable_book_info_from_template.py
fds/sdk/BookBuilder/model/enable_book_list_info.py
fds/sdk/BookBuilder/model/enable_template_info.py
fds/sdk/BookBuilder/model/enable_template_info_post.py
fds/sdk/BookBuilder/model/error_item.py
fds/sdk/BookBuilder/model/invalid_available_report_request.py
fds/sdk/BookBuilder/model/invalid_create_book_from_template_request.py
fds/sdk/BookBuilder/model/invalid_create_book_request.py
fds/sdk/BookBuilder/model/invalid_download_book_aws_request.py
fds/sdk/BookBuilder/model/invalid_template_request.py
fds/sdk/BookBuilder/model/invalid_upload_document_request.py
fds/sdk/BookBuilder/model/pagination_options.py
fds/sdk/BookBuilder/model/report_section.py
fds/sdk/BookBuilder/model/template_content_section.py
fds/sdk/BookBuilder/model/template_info.py
fds_sdk_bookbuilder-1.0.0.dist-info/licenses/LICENSE
fds_sdk_bookbuilder-1.0.0.dist-info/METADATA
fds_sdk_bookbuilder-1.0.0.dist-info/WHEEL
fds_sdk_bookbuilder-1.0.0.dist-info/top_level.txt
fds_sdk_bookbuilder-1.0.0.dist-info/RECORD
